microview/__init__.py
microview/cli.py
microview/file_finder.py
microview/parse_taxonomy.py
microview/plotting.py
microview/rendering.py
microview/schemas/__init__.py
microview/schemas/contrast_table.schema.json
microview/schemas/kaiju_report.schema.json
microview/templates/__init__.py
microview/templates/base.html
microview/templates/head.html
microview/templates/assets/css/bulma_v0.9.4.min.css
microview/templates/assets/css/custom.css
microview/templates/assets/js/MathJax-2.7.5.js
microview/templates/assets/js/plotly-2.12.1.min.js
MicroView-0.11.0.dist-info/LICENSE
MicroView-0.11.0.dist-info/METADATA
MicroView-0.11.0.dist-info/WHEEL
MicroView-0.11.0.dist-info/entry_points.txt
MicroView-0.11.0.dist-info/top_level.txt
MicroView-0.11.0.dist-info/RECORD
