Metadata-Version: 2.1
Name: MicroView
Version: 0.11.0
Summary: Generate reports from metagenomics data
Home-page: https://github.com/jvfe/microview
Author: João Vitor F. Cavalcante
Author-email: jvfe@ufrn.edu.br
License: BSD license
Project-URL: Bug Tracker, https://github.com/jvfe/microview/issues
Project-URL: Documentation, https://jvfe.github.io/microview/
Project-URL: Source Code, https://github.com/jvfe/microview
Keywords: metagenomics workflow visualization report
Classifier: Development Status :: 3 - Alpha
Classifier: Intended Audience :: Science/Research
Classifier: Topic :: Scientific/Engineering :: Bio-Informatics
Classifier: License :: OSI Approved :: BSD License
Classifier: Programming Language :: Python :: 3.8
Classifier: Natural Language :: English
Requires-Python: >=3.8
License-File: LICENSE
Requires-Dist: scipy
Requires-Dist: scikit-bio
Requires-Dist: pandas
Requires-Dist: numpy
Requires-Dist: plotly
Requires-Dist: jinja2
Requires-Dist: rich
Requires-Dist: rich-click
Requires-Dist: click-option-group
Requires-Dist: frictionless <5,>=4.32.0
Provides-Extra: dev
Requires-Dist: mkdocs ; extra == 'dev'
Requires-Dist: mkdocstrings ; extra == 'dev'
Requires-Dist: mkdocstrings.python ; extra == 'dev'
Requires-Dist: click ; extra == 'dev'
Requires-Dist: wheel ; extra == 'dev'
Requires-Dist: twine ; extra == 'dev'
